{"nodes": [{"id": "home_mihir_codes_reflectos_backend_ml_outfit_model_py", "label": "outfit_model.py", "file_type": "code", "source_file": "/home/mihir/Codes/ReflectOS/backend/ml/outfit_model.py", "source_location": "L1"}, {"id": "ml_outfit_model_analyze_outfit", "label": "analyze_outfit()", "file_type": "code", "source_file": "/home/mihir/Codes/ReflectOS/backend/ml/outfit_model.py", "source_location": "L2"}, {"id": "ml_outfit_model_rationale_3", "label": "Placeholder for outfit analysis model.     Returns a list of suggestion dictiona", "file_type": "rationale", "source_file": "/home/mihir/Codes/ReflectOS/backend/ml/outfit_model.py", "source_location": "L3"}], "edges": [{"source": "home_mihir_codes_reflectos_backend_ml_outfit_model_py", "target": "ml_outfit_model_analyze_outfit", "relation": "contains", "confidence": "EXTRACTED", "source_file": "/home/mihir/Codes/ReflectOS/backend/ml/outfit_model.py", "source_location": "L2", "weight": 1.0}, {"source": "ml_outfit_model_rationale_3", "target": "ml_outfit_model_analyze_outfit", "relation": "rationale_for", "confidence": "EXTRACTED", "source_file": "/home/mihir/Codes/ReflectOS/backend/ml/outfit_model.py", "source_location": "L3", "weight": 1.0}], "raw_calls": [{"caller_nid": "ml_outfit_model_analyze_outfit", "callee": "print", "is_member_call": false, "source_file": "/home/mihir/Codes/ReflectOS/backend/ml/outfit_model.py", "source_location": "L7"}]}